deling/__init__.py
deling/authenticators/__init__.py
deling/authenticators/ssh.py
deling/clients/__init__.py
deling/clients/ssh.py
deling/io/__init__.py
deling/io/async.py
deling/io/datastores/__init__.py
deling/io/datastores/core.py
deling/io/datastores/erda.py
deling/io/datastores/file.py
deling/utils/__init__.py
deling/utils/io.py
deling/utils/run.py
deling-0.3.0.dist-info/licenses/LICENSE
deling-0.3.0.dist-info/METADATA
deling-0.3.0.dist-info/WHEEL
deling-0.3.0.dist-info/top_level.txt
deling-0.3.0.dist-info/RECORD
