Metadata-Version: 2.4
Name: deling
Version: 0.3.0
Summary: A library for accessing and storing data in remote storage systems
Home-page: https://github.com/rasmunk/deling
Author: Rasmus Munk
Author-email: munk1@live.dk
License: GNU General Public License v2 (GPLv2)
Project-URL: Source Code, https://github.com/rasmunk/deling
Keywords: Data IO,Staging data,Data transfer,Data storage,Data management
Classifier: Intended Audience :: Developers
Classifier: Intended Audience :: Science/Research
Classifier: License :: OSI Approved :: GNU General Public License v2 (GPLv2)
Classifier: Programming Language :: Python
Classifier: Programming Language :: Python :: 3.8
Classifier: Programming Language :: Python :: 3.9
Classifier: Programming Language :: Python :: 3.10
License-File: LICENSE
Requires-Dist: fs.sshfs>=1.0.2
Requires-Dist: fs>=2.4.16
Requires-Dist: ssh2-python<=1.0.0; python_version <= "3.9"
Requires-Dist: ssh2-python>=1.1.1; python_version >= "3.10"
Requires-Dist: PyYAML>=6.0.1
Provides-Extra: test
Requires-Dist: docutils>=0.18.1; extra == "test"
Requires-Dist: Pygments>=2.15.0; extra == "test"
Requires-Dist: docker>=6.1.3; extra == "test"
Requires-Dist: pytest>=7.1.2; extra == "test"
Provides-Extra: dev
Requires-Dist: black==24.3.0; extra == "dev"
Requires-Dist: docutils==0.18.1; extra == "dev"
Requires-Dist: flake8==4.0.1; extra == "dev"
Requires-Dist: Pygments==2.15.0; extra == "dev"
Dynamic: author
Dynamic: author-email
Dynamic: classifier
Dynamic: description
Dynamic: home-page
Dynamic: keywords
Dynamic: license
Dynamic: license-file
Dynamic: project-url
Dynamic: provides-extra
Dynamic: requires-dist
Dynamic: summary
